<?xml version="1.0" encoding="utf-8" ?>
<dwsync>
<file name="animate.css" server="access818264003.webspace-data.io" local="132756837280000000" remote="132756837280000000" Dst="2" />
<file name="bootstrap.min.css" server="access818264003.webspace-data.io" local="132756837280000000" remote="132756837280000000" Dst="2" />
<file name="camera.css" server="access818264003.webspace-data.io" local="132756837280000000" remote="132756837280000000" Dst="2" />
<file name="custom.css" server="access818264003.webspace-data.io" local="132756837280000000" remote="132756837280000000" Dst="2" />
<file name="flaticon.css" server="access818264003.webspace-data.io" local="132756837280000000" remote="132756837280000000" Dst="2" />
<file name="font-awesome.css" server="access818264003.webspace-data.io" local="132756837280000000" remote="132756837280000000" Dst="2" />
<file name="font-awesome.min.css" server="access818264003.webspace-data.io" local="132756837280000000" remote="132756837280000000" Dst="2" />
<file name="jquery.fatNav.min.css" server="access818264003.webspace-data.io" local="132756837280000000" remote="132756837280000000" Dst="2" />
<file name="owl.carousel.css" server="access818264003.webspace-data.io" local="132756837280000000" remote="132756837280000000" Dst="2" />
<file name="prettyPhoto.css" server="access818264003.webspace-data.io" local="132756837280000000" remote="132756837280000000" Dst="2" />
<file name="responsive.css" server="access818264003.webspace-data.io" local="132756837280000000" remote="132756837280000000" Dst="2" />
<file name="versions.css" server="access818264003.webspace-data.io" local="132756837280000000" remote="132756837280000000" Dst="2" />
</dwsync>