<?xml version="1.0" encoding="utf-8" ?>
<dwsync>
<file name="android-icon-192x192.png" server="access818264003.webspace-data.io" local="132886787520309828" remote="132887385800000000" Dst="1" />
<file name="apple-icon-114x114.png" server="access818264003.webspace-data.io" local="132886788138516747" remote="132887385800000000" Dst="1" />
<file name="apple-icon-120x120.png" server="access818264003.webspace-data.io" local="132886788290505648" remote="132887385800000000" Dst="1" />
<file name="apple-icon-144x144.png" server="access818264003.webspace-data.io" local="132886788367192140" remote="132887385800000000" Dst="1" />
<file name="apple-icon-152x152.png" server="access818264003.webspace-data.io" local="132886788443759593" remote="132887385810000000" Dst="1" />
<file name="apple-icon-180x180.png" server="access818264003.webspace-data.io" local="132886788523457926" remote="132887385810000000" Dst="1" />
<file name="apple-icon-57x57.png" server="access818264003.webspace-data.io" local="132886787606404951" remote="132887385810000000" Dst="1" />
<file name="apple-icon-60x60.png" server="access818264003.webspace-data.io" local="132886787690591724" remote="132887385810000000" Dst="1" />
<file name="apple-icon-72x72.png" server="access818264003.webspace-data.io" local="132886787783812640" remote="132887385810000000" Dst="1" />
<file name="apple-icon-76x76.png" server="access818264003.webspace-data.io" local="132886787945280777" remote="132887385820000000" Dst="1" />
<file name="browserconfig.xml" server="access818264003.webspace-data.io" local="132874561692657991" remote="132875958550000000" Dst="1" />
<file name="favicon-16x16.png" server="access818264003.webspace-data.io" local="132886788625854085" remote="132887385820000000" Dst="1" />
<file name="favicon-256x256.png" server="access818264003.webspace-data.io" local="132886788850884473" remote="132887385820000000" Dst="1" />
<file name="favicon-32x32.png" server="access818264003.webspace-data.io" local="132886790510839180" remote="132887385820000000" Dst="1" />
<file name="favicon-96x96.png" server="access818264003.webspace-data.io" local="132886788757644239" remote="132887385830000000" Dst="1" />
<file name="favicon.ico" server="access818264003.webspace-data.io" local="132910869291756394" remote="132910869670000000" Dst="1" />
<file name="manifest.json" server="access818264003.webspace-data.io" local="132874561694242804" remote="132875958570000000" Dst="1" />
<file name="ms-icon-144x144.png" server="access818264003.webspace-data.io" local="132886788976833946" remote="132887385830000000" Dst="1" />
<file name="ms-icon-150x150.png" server="access818264003.webspace-data.io" local="132886789041867507" remote="132887385830000000" Dst="1" />
<file name="ms-icon-310x310.png" server="access818264003.webspace-data.io" local="132886789116302903" remote="132887385840000000" Dst="1" />
<file name="ms-icon-70x70.png" server="access818264003.webspace-data.io" local="132886788921812571" remote="132887385840000000" Dst="1" />
</dwsync>